xarray_map/__init__.py
xarray_map/plot_folium.py
xarray_map/kmz/__init__.py
xrmap-0.0.8.dist-info/METADATA
xrmap-0.0.8.dist-info/WHEEL
xrmap-0.0.8.dist-info/top_level.txt
xrmap-0.0.8.dist-info/RECORD
