Metadata-Version: 2.1
Name: xrmap
Version: 0.0.8
Summary: Plot xarrays lat-lon datasets using folium
Home-page: https://github.com/javiergvaldecasas/xarray-map
Author: Javier García-Valdecasas
Author-email: garciavaldecasas@oritiayboreas.com
License: Apache-2.0
Platform: UNKNOWN
Classifier: Development Status :: 5 - Production/Stable
Classifier: License :: OSI Approved :: Apache Software License
Classifier: Operating System :: OS Independent
Classifier: Intended Audience :: Science/Research
Classifier: Programming Language :: Python
Classifier: Programming Language :: Python :: 3
Classifier: Programming Language :: Python :: 3.8
Classifier: Programming Language :: Python :: 3.9
Classifier: Programming Language :: Python :: 3.10
Classifier: Programming Language :: Python :: 3.11
Classifier: Topic :: Scientific/Engineering
Requires-Python: >=3.6
Requires-Dist: xarray (>=0.20)
Requires-Dist: folium
Requires-Dist: matplotlib
